bittrex_websocket/__init__.py
bittrex_websocket/_abc.py
bittrex_websocket/_auxiliary.py
bittrex_websocket/_exceptions.py
bittrex_websocket/_logger.py
bittrex_websocket/_queue_events.py
bittrex_websocket/_signalr.py
bittrex_websocket/constants.py
bittrex_websocket/order_book.py
bittrex_websocket/websocket_client-legacy.py
bittrex_websocket/websocket_client.py
bittrex_websocket/websocket_client_aio-old.py
bittrex_websocket/examples/__init__.py
bittrex_websocket/examples/order_book.py
bittrex_websocket/examples/record_trades.py
bittrex_websocket/examples/ticker_updates.py
bittrex_websocket-1.0.6.3.dist-info/METADATA
bittrex_websocket-1.0.6.3.dist-info/RECORD
bittrex_websocket-1.0.6.3.dist-info/WHEEL
bittrex_websocket-1.0.6.3.dist-info/top_level.txt
